{"repos":{"kaboom.js":{"fullName":"robiningelbrecht\/kaboom.js","commitCount":23},"playstation-easy-platinums-chrome-extension":{"fullName":"robiningelbrecht\/playstation-easy-platinums-chrome-extension","commitCount":14},"phpunit-coverage-tools":{"fullName":"robiningelbrecht\/phpunit-coverage-tools","commitCount":39},"playstation-easy-platinums":{"fullName":"robiningelbrecht\/playstation-easy-platinums","commitCount":1678},"speedcubing-glossary":{"fullName":"robiningelbrecht\/speedcubing-glossary","commitCount":23},"presentations.robiningelbrecht.be":{"fullName":"robiningelbrecht\/presentations.robiningelbrecht.be","commitCount":113},"code-scope":{"fullName":"robiningelbrecht\/code-scope","commitCount":4},"vanilla-js-pokedex":{"fullName":"robiningelbrecht\/vanilla-js-pokedex","commitCount":33},"php-cheat-sheet":{"fullName":"robiningelbrecht\/php-cheat-sheet","commitCount":5},"baldwin-condig-test":{"fullName":"robiningelbrecht\/baldwin-condig-test","commitCount":19},"robiningelbrecht":{"fullName":"robiningelbrecht\/robiningelbrecht","commitCount":286},"psn-profile-card":{"fullName":"robiningelbrecht\/psn-profile-card","commitCount":73},"ntfy-action":{"fullName":"robiningelbrecht\/ntfy-action","commitCount":27},"notion-media-cdn":{"fullName":"robiningelbrecht\/notion-media-cdn","commitCount":76},"flippable-card-web-component":{"fullName":"robiningelbrecht\/flippable-card-web-component","commitCount":11},"strava-activities":{"fullName":"robiningelbrecht\/strava-activities","commitCount":364},"medium-rss-github":{"fullName":"robiningelbrecht\/medium-rss-github","commitCount":34},"puzzle-generator":{"fullName":"robiningelbrecht\/puzzle-generator","commitCount":94},"powerpyx-focus":{"fullName":"robiningelbrecht\/powerpyx-focus","commitCount":19},"hook_event_dispatcher":{"fullName":"pdenooijer\/hook_event_dispatcher","commitCount":1},"psnprofiles.robiningelbrecht.be":{"fullName":"robiningelbrecht\/psnprofiles.robiningelbrecht.be","commitCount":75},"wca-rest-api":{"fullName":"robiningelbrecht\/wca-rest-api","commitCount":198},"vanilla-js-cheat-sheet":{"fullName":"robiningelbrecht\/vanilla-js-cheat-sheet","commitCount":5},"drupal-dev-days-2022":{"fullName":"robiningelbrecht\/drupal-dev-days-2022","commitCount":16},"php-slim-skeleton-docs":{"fullName":"robiningelbrecht\/php-slim-skeleton-docs","commitCount":41},"notion-embeds":{"fullName":"robiningelbrecht\/notion-embeds","commitCount":15},"pokemon-memory-game":{"fullName":"robiningelbrecht\/pokemon-memory-game","commitCount":31},"php-slim-skeleton":{"fullName":"robiningelbrecht\/php-slim-skeleton","commitCount":256},"sudoku-solver-vanilla-js":{"fullName":"robiningelbrecht\/sudoku-solver-vanilla-js","commitCount":4},"twisty-puzzle-scrambler":{"fullName":"robiningelbrecht\/twisty-puzzle-scrambler","commitCount":50},"phpunit-coverage-check":{"fullName":"robiningelbrecht\/phpunit-coverage-check","commitCount":45},"reddit-php-client":{"fullName":"robiningelbrecht\/reddit-php-client","commitCount":8},"phpunit-pretty-print":{"fullName":"robiningelbrecht\/phpunit-pretty-print","commitCount":52},"drush-gdpr-dumper":{"fullName":"robiningelbrecht\/drush-gdpr-dumper","commitCount":15},"cs-timer-clone":{"fullName":"robiningelbrecht\/cs-timer-clone","commitCount":10},"airtable-google-sheets-backup":{"fullName":"robiningelbrecht\/airtable-google-sheets-backup","commitCount":8},"cube-scramble":{"fullName":"robiningelbrecht\/cube-scramble","commitCount":50},"configuration":{"fullName":"robiningelbrecht\/configuration","commitCount":3},"psnprofiles-playstation-5-ui":{"fullName":"robiningelbrecht\/psnprofiles-playstation-5-ui","commitCount":64},"psnprofiles-scraper":{"fullName":"robiningelbrecht\/psnprofiles-scraper","commitCount":70},"sorting-algorithms-vanilla-js":{"fullName":"robiningelbrecht\/sorting-algorithms-vanilla-js","commitCount":33},"pokemon-card-generator":{"fullName":"robiningelbrecht\/pokemon-card-generator","commitCount":77},"apache-echarts-action":{"fullName":"robiningelbrecht\/apache-echarts-action","commitCount":22},"docker-browsershot":{"fullName":"robiningelbrecht\/docker-browsershot","commitCount":13},"drupal-amqp-rabbitmq":{"fullName":"robiningelbrecht\/drupal-amqp-rabbitmq","commitCount":93},"gotta-generate-em-all":{"fullName":"robiningelbrecht\/gotta-generate-em-all","commitCount":337},"robiningelbrecht.be":{"fullName":"robiningelbrecht\/robiningelbrecht.be","commitCount":277},"php-design-patterns":{"fullName":"robiningelbrecht\/php-design-patterns","commitCount":52},"playstation-trophy-cards":{"fullName":"robiningelbrecht\/playstation-trophy-cards","commitCount":31},"gpx_field":{"fullName":"f0ns\/gpx_field","commitCount":8},"markdown-bar-chart":{"fullName":"robiningelbrecht\/markdown-bar-chart","commitCount":6},"continuous-integration-example":{"fullName":"robiningelbrecht\/continuous-integration-example","commitCount":123}},"totalCommits":5024,"firstCommit":{"date":"2017-06-16 14:33:50.000000","timezone_type":3,"timezone":"UTC"},"mostRecentCommits":[{"sha":"2704c7ac75d2707708c44ae13e56d0d347940abb","node_id":"C_kwDOJnGb99oAKDI3MDRjN2FjNzVkMjcwNzcwOGM0NGFlMTNlNTZkMGQzNDc5NDBhYmI","commit":{"author":{"name":"robiningelbrecht","email":"robiningelbrecht@users.noreply.github.com","date":"2023-09-19T18:34:58Z"},"committer":{"name":"robiningelbrecht","email":"robiningelbrecht@users.noreply.github.com","date":"2023-09-19T18:34:58Z"},"message":"Updated strava activities","tree":{"sha":"14f4d34b6a3a51c629daf1985ada8e74278b31be","url":"https:\/\/api.github.com\/repos\/robiningelbrecht\/strava-activities\/git\/trees\/14f4d34b6a3a51c629daf1985ada8e74278b31be"},"url":"https:\/\/api.github.com\/repos\/robiningelbrecht\/strava-activities\/git\/commits\/2704c7ac75d2707708c44ae13e56d0d347940abb","comment_count":0,"verification":{"verified":false,"reason":"unsigned","signature":null,"payload":null},"timestamp":1695148498},"url":"https:\/\/api.github.com\/repos\/robiningelbrecht\/strava-activities\/commits\/2704c7ac75d2707708c44ae13e56d0d347940abb","html_url":"https:\/\/github.com\/robiningelbrecht\/strava-activities\/commit\/2704c7ac75d2707708c44ae13e56d0d347940abb","comments_url":"https:\/\/api.github.com\/repos\/robiningelbrecht\/strava-activities\/commits\/2704c7ac75d2707708c44ae13e56d0d347940abb\/comments","author":{"login":"robiningelbrecht","id":203894,"node_id":"MDQ6VXNlcjIwMzg5NA==","avatar_url":"https:\/\/avatars.githubusercontent.com\/u\/203894?v=4","gravatar_id":"","url":"https:\/\/api.github.com\/users\/robiningelbrecht","html_url":"https:\/\/github.com\/robiningelbrecht","followers_url":"https:\/\/api.github.com\/users\/robiningelbrecht\/followers","following_url":"https:\/\/api.github.com\/users\/robiningelbrecht\/following{\/other_user}","gists_url":"https:\/\/api.github.com\/users\/robiningelbrecht\/gists{\/gist_id}","starred_url":"https:\/\/api.github.com\/users\/robiningelbrecht\/starred{\/owner}{\/repo}","subscriptions_url":"https:\/\/api.github.com\/users\/robiningelbrecht\/subscriptions","organizations_url":"https:\/\/api.github.com\/users\/robiningelbrecht\/orgs","repos_url":"https:\/\/api.github.com\/users\/robiningelbrecht\/repos","events_url":"https:\/\/api.github.com\/users\/robiningelbrecht\/events{\/privacy}","received_events_url":"https:\/\/api.github.com\/users\/robiningelbrecht\/received_events","type":"User","site_admin":false},"committer":{"login":"robiningelbrecht","id":203894,"node_id":"MDQ6VXNlcjIwMzg5NA==","avatar_url":"https:\/\/avatars.githubusercontent.com\/u\/203894?v=4","gravatar_id":"","url":"https:\/\/api.github.com\/users\/robiningelbrecht","html_url":"https:\/\/github.com\/robiningelbrecht","followers_url":"https:\/\/api.github.com\/users\/robiningelbrecht\/followers","following_url":"https:\/\/api.github.com\/users\/robiningelbrecht\/following{\/other_user}","gists_url":"https:\/\/api.github.com\/users\/robiningelbrecht\/gists{\/gist_id}","starred_url":"https:\/\/api.github.com\/users\/robiningelbrecht\/starred{\/owner}{\/repo}","subscriptions_url":"https:\/\/api.github.com\/users\/robiningelbrecht\/subscriptions","organizations_url":"https:\/\/api.github.com\/users\/robiningelbrecht\/orgs","repos_url":"https:\/\/api.github.com\/users\/robiningelbrecht\/repos","events_url":"https:\/\/api.github.com\/users\/robiningelbrecht\/events{\/privacy}","received_events_url":"https:\/\/api.github.com\/users\/robiningelbrecht\/received_events","type":"User","site_admin":false},"parents":[{"sha":"e9ec79981141959c59084ccc49b2c9f6686749f0","url":"https:\/\/api.github.com\/repos\/robiningelbrecht\/strava-activities\/commits\/e9ec79981141959c59084ccc49b2c9f6686749f0","html_url":"https:\/\/github.com\/robiningelbrecht\/strava-activities\/commit\/e9ec79981141959c59084ccc49b2c9f6686749f0"}],"_id":350},{"sha":"e9ec79981141959c59084ccc49b2c9f6686749f0","node_id":"C_kwDOJnGb99oAKGU5ZWM3OTk4MTE0MTk1OWM1OTA4NGNjYzQ5YjJjOWY2Njg2NzQ5ZjA","commit":{"author":{"name":"robiningelbrecht","email":"robiningelbrecht@users.noreply.github.com","date":"2023-09-19T18:25:33Z"},"committer":{"name":"robiningelbrecht","email":"robiningelbrecht@users.noreply.github.com","date":"2023-09-19T18:25:33Z"},"message":"Added static cache in Eddington class","tree":{"sha":"ddb12bbe10960b226cea761b43e57d767c09d332","url":"https:\/\/api.github.com\/repos\/robiningelbrecht\/strava-activities\/git\/trees\/ddb12bbe10960b226cea761b43e57d767c09d332"},"url":"https:\/\/api.github.com\/repos\/robiningelbrecht\/strava-activities\/git\/commits\/e9ec79981141959c59084ccc49b2c9f6686749f0","comment_count":0,"verification":{"verified":false,"reason":"unsigned","signature":null,"payload":null},"timestamp":1695147933},"url":"https:\/\/api.github.com\/repos\/robiningelbrecht\/strava-activities\/commits\/e9ec79981141959c59084ccc49b2c9f6686749f0","html_url":"https:\/\/github.com\/robiningelbrecht\/strava-activities\/commit\/e9ec79981141959c59084ccc49b2c9f6686749f0","comments_url":"https:\/\/api.github.com\/repos\/robiningelbrecht\/strava-activities\/commits\/e9ec79981141959c59084ccc49b2c9f6686749f0\/comments","author":{"login":"robiningelbrecht","id":203894,"node_id":"MDQ6VXNlcjIwMzg5NA==","avatar_url":"https:\/\/avatars.githubusercontent.com\/u\/203894?v=4","gravatar_id":"","url":"https:\/\/api.github.com\/users\/robiningelbrecht","html_url":"https:\/\/github.com\/robiningelbrecht","followers_url":"https:\/\/api.github.com\/users\/robiningelbrecht\/followers","following_url":"https:\/\/api.github.com\/users\/robiningelbrecht\/following{\/other_user}","gists_url":"https:\/\/api.github.com\/users\/robiningelbrecht\/gists{\/gist_id}","starred_url":"https:\/\/api.github.com\/users\/robiningelbrecht\/starred{\/owner}{\/repo}","subscriptions_url":"https:\/\/api.github.com\/users\/robiningelbrecht\/subscriptions","organizations_url":"https:\/\/api.github.com\/users\/robiningelbrecht\/orgs","repos_url":"https:\/\/api.github.com\/users\/robiningelbrecht\/repos","events_url":"https:\/\/api.github.com\/users\/robiningelbrecht\/events{\/privacy}","received_events_url":"https:\/\/api.github.com\/users\/robiningelbrecht\/received_events","type":"User","site_admin":false},"committer":{"login":"robiningelbrecht","id":203894,"node_id":"MDQ6VXNlcjIwMzg5NA==","avatar_url":"https:\/\/avatars.githubusercontent.com\/u\/203894?v=4","gravatar_id":"","url":"https:\/\/api.github.com\/users\/robiningelbrecht","html_url":"https:\/\/github.com\/robiningelbrecht","followers_url":"https:\/\/api.github.com\/users\/robiningelbrecht\/followers","following_url":"https:\/\/api.github.com\/users\/robiningelbrecht\/following{\/other_user}","gists_url":"https:\/\/api.github.com\/users\/robiningelbrecht\/gists{\/gist_id}","starred_url":"https:\/\/api.github.com\/users\/robiningelbrecht\/starred{\/owner}{\/repo}","subscriptions_url":"https:\/\/api.github.com\/users\/robiningelbrecht\/subscriptions","organizations_url":"https:\/\/api.github.com\/users\/robiningelbrecht\/orgs","repos_url":"https:\/\/api.github.com\/users\/robiningelbrecht\/repos","events_url":"https:\/\/api.github.com\/users\/robiningelbrecht\/events{\/privacy}","received_events_url":"https:\/\/api.github.com\/users\/robiningelbrecht\/received_events","type":"User","site_admin":false},"parents":[{"sha":"f13c9b8c1283a09d308338dec8d558bbd48e5aeb","url":"https:\/\/api.github.com\/repos\/robiningelbrecht\/strava-activities\/commits\/f13c9b8c1283a09d308338dec8d558bbd48e5aeb","html_url":"https:\/\/github.com\/robiningelbrecht\/strava-activities\/commit\/f13c9b8c1283a09d308338dec8d558bbd48e5aeb"}],"_id":351},{"sha":"f13c9b8c1283a09d308338dec8d558bbd48e5aeb","node_id":"C_kwDOJnGb99oAKGYxM2M5YjhjMTI4M2EwOWQzMDgzMzhkZWM4ZDU1OGJiZDQ4ZTVhZWI","commit":{"author":{"name":"robiningelbrecht","email":"robiningelbrecht@users.noreply.github.com","date":"2023-09-19T18:21:02Z"},"committer":{"name":"robiningelbrecht","email":"robiningelbrecht@users.noreply.github.com","date":"2023-09-19T18:21:02Z"},"message":"Added RPM","tree":{"sha":"48474ad4f13131d8af9225ade7e430347fc2ca8c","url":"https:\/\/api.github.com\/repos\/robiningelbrecht\/strava-activities\/git\/trees\/48474ad4f13131d8af9225ade7e430347fc2ca8c"},"url":"https:\/\/api.github.com\/repos\/robiningelbrecht\/strava-activities\/git\/commits\/f13c9b8c1283a09d308338dec8d558bbd48e5aeb","comment_count":0,"verification":{"verified":false,"reason":"unsigned","signature":null,"payload":null},"timestamp":1695147662},"url":"https:\/\/api.github.com\/repos\/robiningelbrecht\/strava-activities\/commits\/f13c9b8c1283a09d308338dec8d558bbd48e5aeb","html_url":"https:\/\/github.com\/robiningelbrecht\/strava-activities\/commit\/f13c9b8c1283a09d308338dec8d558bbd48e5aeb","comments_url":"https:\/\/api.github.com\/repos\/robiningelbrecht\/strava-activities\/commits\/f13c9b8c1283a09d308338dec8d558bbd48e5aeb\/comments","author":{"login":"robiningelbrecht","id":203894,"node_id":"MDQ6VXNlcjIwMzg5NA==","avatar_url":"https:\/\/avatars.githubusercontent.com\/u\/203894?v=4","gravatar_id":"","url":"https:\/\/api.github.com\/users\/robiningelbrecht","html_url":"https:\/\/github.com\/robiningelbrecht","followers_url":"https:\/\/api.github.com\/users\/robiningelbrecht\/followers","following_url":"https:\/\/api.github.com\/users\/robiningelbrecht\/following{\/other_user}","gists_url":"https:\/\/api.github.com\/users\/robiningelbrecht\/gists{\/gist_id}","starred_url":"https:\/\/api.github.com\/users\/robiningelbrecht\/starred{\/owner}{\/repo}","subscriptions_url":"https:\/\/api.github.com\/users\/robiningelbrecht\/subscriptions","organizations_url":"https:\/\/api.github.com\/users\/robiningelbrecht\/orgs","repos_url":"https:\/\/api.github.com\/users\/robiningelbrecht\/repos","events_url":"https:\/\/api.github.com\/users\/robiningelbrecht\/events{\/privacy}","received_events_url":"https:\/\/api.github.com\/users\/robiningelbrecht\/received_events","type":"User","site_admin":false},"committer":{"login":"robiningelbrecht","id":203894,"node_id":"MDQ6VXNlcjIwMzg5NA==","avatar_url":"https:\/\/avatars.githubusercontent.com\/u\/203894?v=4","gravatar_id":"","url":"https:\/\/api.github.com\/users\/robiningelbrecht","html_url":"https:\/\/github.com\/robiningelbrecht","followers_url":"https:\/\/api.github.com\/users\/robiningelbrecht\/followers","following_url":"https:\/\/api.github.com\/users\/robiningelbrecht\/following{\/other_user}","gists_url":"https:\/\/api.github.com\/users\/robiningelbrecht\/gists{\/gist_id}","starred_url":"https:\/\/api.github.com\/users\/robiningelbrecht\/starred{\/owner}{\/repo}","subscriptions_url":"https:\/\/api.github.com\/users\/robiningelbrecht\/subscriptions","organizations_url":"https:\/\/api.github.com\/users\/robiningelbrecht\/orgs","repos_url":"https:\/\/api.github.com\/users\/robiningelbrecht\/repos","events_url":"https:\/\/api.github.com\/users\/robiningelbrecht\/events{\/privacy}","received_events_url":"https:\/\/api.github.com\/users\/robiningelbrecht\/received_events","type":"User","site_admin":false},"parents":[{"sha":"bb081dbfba32fd005f5b0d8a10e7b2a71cad0328","url":"https:\/\/api.github.com\/repos\/robiningelbrecht\/strava-activities\/commits\/bb081dbfba32fd005f5b0d8a10e7b2a71cad0328","html_url":"https:\/\/github.com\/robiningelbrecht\/strava-activities\/commit\/bb081dbfba32fd005f5b0d8a10e7b2a71cad0328"}],"_id":352},{"sha":"bb081dbfba32fd005f5b0d8a10e7b2a71cad0328","node_id":"C_kwDOJnGb99oAKGJiMDgxZGJmYmEzMmZkMDA1ZjViMGQ4YTEwZTdiMmE3MWNhZDAzMjg","commit":{"author":{"name":"robiningelbrecht","email":"robiningelbrecht@users.noreply.github.com","date":"2023-09-19T18:08:18Z"},"committer":{"name":"robiningelbrecht","email":"robiningelbrecht@users.noreply.github.com","date":"2023-09-19T18:08:18Z"},"message":"Eddington changes","tree":{"sha":"99eb82bcaf7004ca0ebd192a89194a2d186d47f9","url":"https:\/\/api.github.com\/repos\/robiningelbrecht\/strava-activities\/git\/trees\/99eb82bcaf7004ca0ebd192a89194a2d186d47f9"},"url":"https:\/\/api.github.com\/repos\/robiningelbrecht\/strava-activities\/git\/commits\/bb081dbfba32fd005f5b0d8a10e7b2a71cad0328","comment_count":0,"verification":{"verified":false,"reason":"unsigned","signature":null,"payload":null},"timestamp":1695146898},"url":"https:\/\/api.github.com\/repos\/robiningelbrecht\/strava-activities\/commits\/bb081dbfba32fd005f5b0d8a10e7b2a71cad0328","html_url":"https:\/\/github.com\/robiningelbrecht\/strava-activities\/commit\/bb081dbfba32fd005f5b0d8a10e7b2a71cad0328","comments_url":"https:\/\/api.github.com\/repos\/robiningelbrecht\/strava-activities\/commits\/bb081dbfba32fd005f5b0d8a10e7b2a71cad0328\/comments","author":{"login":"robiningelbrecht","id":203894,"node_id":"MDQ6VXNlcjIwMzg5NA==","avatar_url":"https:\/\/avatars.githubusercontent.com\/u\/203894?v=4","gravatar_id":"","url":"https:\/\/api.github.com\/users\/robiningelbrecht","html_url":"https:\/\/github.com\/robiningelbrecht","followers_url":"https:\/\/api.github.com\/users\/robiningelbrecht\/followers","following_url":"https:\/\/api.github.com\/users\/robiningelbrecht\/following{\/other_user}","gists_url":"https:\/\/api.github.com\/users\/robiningelbrecht\/gists{\/gist_id}","starred_url":"https:\/\/api.github.com\/users\/robiningelbrecht\/starred{\/owner}{\/repo}","subscriptions_url":"https:\/\/api.github.com\/users\/robiningelbrecht\/subscriptions","organizations_url":"https:\/\/api.github.com\/users\/robiningelbrecht\/orgs","repos_url":"https:\/\/api.github.com\/users\/robiningelbrecht\/repos","events_url":"https:\/\/api.github.com\/users\/robiningelbrecht\/events{\/privacy}","received_events_url":"https:\/\/api.github.com\/users\/robiningelbrecht\/received_events","type":"User","site_admin":false},"committer":{"login":"robiningelbrecht","id":203894,"node_id":"MDQ6VXNlcjIwMzg5NA==","avatar_url":"https:\/\/avatars.githubusercontent.com\/u\/203894?v=4","gravatar_id":"","url":"https:\/\/api.github.com\/users\/robiningelbrecht","html_url":"https:\/\/github.com\/robiningelbrecht","followers_url":"https:\/\/api.github.com\/users\/robiningelbrecht\/followers","following_url":"https:\/\/api.github.com\/users\/robiningelbrecht\/following{\/other_user}","gists_url":"https:\/\/api.github.com\/users\/robiningelbrecht\/gists{\/gist_id}","starred_url":"https:\/\/api.github.com\/users\/robiningelbrecht\/starred{\/owner}{\/repo}","subscriptions_url":"https:\/\/api.github.com\/users\/robiningelbrecht\/subscriptions","organizations_url":"https:\/\/api.github.com\/users\/robiningelbrecht\/orgs","repos_url":"https:\/\/api.github.com\/users\/robiningelbrecht\/repos","events_url":"https:\/\/api.github.com\/users\/robiningelbrecht\/events{\/privacy}","received_events_url":"https:\/\/api.github.com\/users\/robiningelbrecht\/received_events","type":"User","site_admin":false},"parents":[{"sha":"e943b6371f75ae581f745f08fad7920ad12910da","url":"https:\/\/api.github.com\/repos\/robiningelbrecht\/strava-activities\/commits\/e943b6371f75ae581f745f08fad7920ad12910da","html_url":"https:\/\/github.com\/robiningelbrecht\/strava-activities\/commit\/e943b6371f75ae581f745f08fad7920ad12910da"}],"_id":353},{"sha":"e943b6371f75ae581f745f08fad7920ad12910da","node_id":"C_kwDOJnGb99oAKGU5NDNiNjM3MWY3NWFlNTgxZjc0NWYwOGZhZDc5MjBhZDEyOTEwZGE","commit":{"author":{"name":"robiningelbrecht","email":"robiningelbrecht@users.noreply.github.com","date":"2023-09-19T18:04:48Z"},"committer":{"name":"robiningelbrecht","email":"robiningelbrecht@users.noreply.github.com","date":"2023-09-19T18:04:48Z"},"message":"Eddington changes","tree":{"sha":"e3e91dd1f43a3e29dedf3e3e46dfa47b9efe6c82","url":"https:\/\/api.github.com\/repos\/robiningelbrecht\/strava-activities\/git\/trees\/e3e91dd1f43a3e29dedf3e3e46dfa47b9efe6c82"},"url":"https:\/\/api.github.com\/repos\/robiningelbrecht\/strava-activities\/git\/commits\/e943b6371f75ae581f745f08fad7920ad12910da","comment_count":0,"verification":{"verified":false,"reason":"unsigned","signature":null,"payload":null},"timestamp":1695146688},"url":"https:\/\/api.github.com\/repos\/robiningelbrecht\/strava-activities\/commits\/e943b6371f75ae581f745f08fad7920ad12910da","html_url":"https:\/\/github.com\/robiningelbrecht\/strava-activities\/commit\/e943b6371f75ae581f745f08fad7920ad12910da","comments_url":"https:\/\/api.github.com\/repos\/robiningelbrecht\/strava-activities\/commits\/e943b6371f75ae581f745f08fad7920ad12910da\/comments","author":{"login":"robiningelbrecht","id":203894,"node_id":"MDQ6VXNlcjIwMzg5NA==","avatar_url":"https:\/\/avatars.githubusercontent.com\/u\/203894?v=4","gravatar_id":"","url":"https:\/\/api.github.com\/users\/robiningelbrecht","html_url":"https:\/\/github.com\/robiningelbrecht","followers_url":"https:\/\/api.github.com\/users\/robiningelbrecht\/followers","following_url":"https:\/\/api.github.com\/users\/robiningelbrecht\/following{\/other_user}","gists_url":"https:\/\/api.github.com\/users\/robiningelbrecht\/gists{\/gist_id}","starred_url":"https:\/\/api.github.com\/users\/robiningelbrecht\/starred{\/owner}{\/repo}","subscriptions_url":"https:\/\/api.github.com\/users\/robiningelbrecht\/subscriptions","organizations_url":"https:\/\/api.github.com\/users\/robiningelbrecht\/orgs","repos_url":"https:\/\/api.github.com\/users\/robiningelbrecht\/repos","events_url":"https:\/\/api.github.com\/users\/robiningelbrecht\/events{\/privacy}","received_events_url":"https:\/\/api.github.com\/users\/robiningelbrecht\/received_events","type":"User","site_admin":false},"committer":{"login":"robiningelbrecht","id":203894,"node_id":"MDQ6VXNlcjIwMzg5NA==","avatar_url":"https:\/\/avatars.githubusercontent.com\/u\/203894?v=4","gravatar_id":"","url":"https:\/\/api.github.com\/users\/robiningelbrecht","html_url":"https:\/\/github.com\/robiningelbrecht","followers_url":"https:\/\/api.github.com\/users\/robiningelbrecht\/followers","following_url":"https:\/\/api.github.com\/users\/robiningelbrecht\/following{\/other_user}","gists_url":"https:\/\/api.github.com\/users\/robiningelbrecht\/gists{\/gist_id}","starred_url":"https:\/\/api.github.com\/users\/robiningelbrecht\/starred{\/owner}{\/repo}","subscriptions_url":"https:\/\/api.github.com\/users\/robiningelbrecht\/subscriptions","organizations_url":"https:\/\/api.github.com\/users\/robiningelbrecht\/orgs","repos_url":"https:\/\/api.github.com\/users\/robiningelbrecht\/repos","events_url":"https:\/\/api.github.com\/users\/robiningelbrecht\/events{\/privacy}","received_events_url":"https:\/\/api.github.com\/users\/robiningelbrecht\/received_events","type":"User","site_admin":false},"parents":[{"sha":"2afedc302002dba6071babcc8ffea42018a3b988","url":"https:\/\/api.github.com\/repos\/robiningelbrecht\/strava-activities\/commits\/2afedc302002dba6071babcc8ffea42018a3b988","html_url":"https:\/\/github.com\/robiningelbrecht\/strava-activities\/commit\/2afedc302002dba6071babcc8ffea42018a3b988"}],"_id":354},{"sha":"2afedc302002dba6071babcc8ffea42018a3b988","node_id":"C_kwDOJnGb99oAKDJhZmVkYzMwMjAwMmRiYTYwNzFiYWJjYzhmZmVhNDIwMThhM2I5ODg","commit":{"author":{"name":"robiningelbrecht","email":"robiningelbrecht@users.noreply.github.com","date":"2023-09-19T17:55:05Z"},"committer":{"name":"robiningelbrecht","email":"robiningelbrecht@users.noreply.github.com","date":"2023-09-19T17:55:05Z"},"message":"Align table","tree":{"sha":"ac7bc48433e5e1f003473ca86c4ffdc85aa3f49c","url":"https:\/\/api.github.com\/repos\/robiningelbrecht\/strava-activities\/git\/trees\/ac7bc48433e5e1f003473ca86c4ffdc85aa3f49c"},"url":"https:\/\/api.github.com\/repos\/robiningelbrecht\/strava-activities\/git\/commits\/2afedc302002dba6071babcc8ffea42018a3b988","comment_count":0,"verification":{"verified":false,"reason":"unsigned","signature":null,"payload":null},"timestamp":1695146105},"url":"https:\/\/api.github.com\/repos\/robiningelbrecht\/strava-activities\/commits\/2afedc302002dba6071babcc8ffea42018a3b988","html_url":"https:\/\/github.com\/robiningelbrecht\/strava-activities\/commit\/2afedc302002dba6071babcc8ffea42018a3b988","comments_url":"https:\/\/api.github.com\/repos\/robiningelbrecht\/strava-activities\/commits\/2afedc302002dba6071babcc8ffea42018a3b988\/comments","author":{"login":"robiningelbrecht","id":203894,"node_id":"MDQ6VXNlcjIwMzg5NA==","avatar_url":"https:\/\/avatars.githubusercontent.com\/u\/203894?v=4","gravatar_id":"","url":"https:\/\/api.github.com\/users\/robiningelbrecht","html_url":"https:\/\/github.com\/robiningelbrecht","followers_url":"https:\/\/api.github.com\/users\/robiningelbrecht\/followers","following_url":"https:\/\/api.github.com\/users\/robiningelbrecht\/following{\/other_user}","gists_url":"https:\/\/api.github.com\/users\/robiningelbrecht\/gists{\/gist_id}","starred_url":"https:\/\/api.github.com\/users\/robiningelbrecht\/starred{\/owner}{\/repo}","subscriptions_url":"https:\/\/api.github.com\/users\/robiningelbrecht\/subscriptions","organizations_url":"https:\/\/api.github.com\/users\/robiningelbrecht\/orgs","repos_url":"https:\/\/api.github.com\/users\/robiningelbrecht\/repos","events_url":"https:\/\/api.github.com\/users\/robiningelbrecht\/events{\/privacy}","received_events_url":"https:\/\/api.github.com\/users\/robiningelbrecht\/received_events","type":"User","site_admin":false},"committer":{"login":"robiningelbrecht","id":203894,"node_id":"MDQ6VXNlcjIwMzg5NA==","avatar_url":"https:\/\/avatars.githubusercontent.com\/u\/203894?v=4","gravatar_id":"","url":"https:\/\/api.github.com\/users\/robiningelbrecht","html_url":"https:\/\/github.com\/robiningelbrecht","followers_url":"https:\/\/api.github.com\/users\/robiningelbrecht\/followers","following_url":"https:\/\/api.github.com\/users\/robiningelbrecht\/following{\/other_user}","gists_url":"https:\/\/api.github.com\/users\/robiningelbrecht\/gists{\/gist_id}","starred_url":"https:\/\/api.github.com\/users\/robiningelbrecht\/starred{\/owner}{\/repo}","subscriptions_url":"https:\/\/api.github.com\/users\/robiningelbrecht\/subscriptions","organizations_url":"https:\/\/api.github.com\/users\/robiningelbrecht\/orgs","repos_url":"https:\/\/api.github.com\/users\/robiningelbrecht\/repos","events_url":"https:\/\/api.github.com\/users\/robiningelbrecht\/events{\/privacy}","received_events_url":"https:\/\/api.github.com\/users\/robiningelbrecht\/received_events","type":"User","site_admin":false},"parents":[{"sha":"a7b393de41fc14c8eba7a83a176a5041b81b10a6","url":"https:\/\/api.github.com\/repos\/robiningelbrecht\/strava-activities\/commits\/a7b393de41fc14c8eba7a83a176a5041b81b10a6","html_url":"https:\/\/github.com\/robiningelbrecht\/strava-activities\/commit\/a7b393de41fc14c8eba7a83a176a5041b81b10a6"}],"_id":355},{"sha":"a7b393de41fc14c8eba7a83a176a5041b81b10a6","node_id":"C_kwDOJnGb99oAKGE3YjM5M2RlNDFmYzE0YzhlYmE3YTgzYTE3NmE1MDQxYjgxYjEwYTY","commit":{"author":{"name":"robiningelbrecht","email":"robiningelbrecht@users.noreply.github.com","date":"2023-09-19T14:48:21Z"},"committer":{"name":"robiningelbrecht","email":"robiningelbrecht@users.noreply.github.com","date":"2023-09-19T14:48:21Z"},"message":"Hide older activities","tree":{"sha":"0dfc631a3a17085f3c5aafd4b886d1c6ba0c5ddf","url":"https:\/\/api.github.com\/repos\/robiningelbrecht\/strava-activities\/git\/trees\/0dfc631a3a17085f3c5aafd4b886d1c6ba0c5ddf"},"url":"https:\/\/api.github.com\/repos\/robiningelbrecht\/strava-activities\/git\/commits\/a7b393de41fc14c8eba7a83a176a5041b81b10a6","comment_count":0,"verification":{"verified":false,"reason":"unsigned","signature":null,"payload":null},"timestamp":1695134901},"url":"https:\/\/api.github.com\/repos\/robiningelbrecht\/strava-activities\/commits\/a7b393de41fc14c8eba7a83a176a5041b81b10a6","html_url":"https:\/\/github.com\/robiningelbrecht\/strava-activities\/commit\/a7b393de41fc14c8eba7a83a176a5041b81b10a6","comments_url":"https:\/\/api.github.com\/repos\/robiningelbrecht\/strava-activities\/commits\/a7b393de41fc14c8eba7a83a176a5041b81b10a6\/comments","author":{"login":"robiningelbrecht","id":203894,"node_id":"MDQ6VXNlcjIwMzg5NA==","avatar_url":"https:\/\/avatars.githubusercontent.com\/u\/203894?v=4","gravatar_id":"","url":"https:\/\/api.github.com\/users\/robiningelbrecht","html_url":"https:\/\/github.com\/robiningelbrecht","followers_url":"https:\/\/api.github.com\/users\/robiningelbrecht\/followers","following_url":"https:\/\/api.github.com\/users\/robiningelbrecht\/following{\/other_user}","gists_url":"https:\/\/api.github.com\/users\/robiningelbrecht\/gists{\/gist_id}","starred_url":"https:\/\/api.github.com\/users\/robiningelbrecht\/starred{\/owner}{\/repo}","subscriptions_url":"https:\/\/api.github.com\/users\/robiningelbrecht\/subscriptions","organizations_url":"https:\/\/api.github.com\/users\/robiningelbrecht\/orgs","repos_url":"https:\/\/api.github.com\/users\/robiningelbrecht\/repos","events_url":"https:\/\/api.github.com\/users\/robiningelbrecht\/events{\/privacy}","received_events_url":"https:\/\/api.github.com\/users\/robiningelbrecht\/received_events","type":"User","site_admin":false},"committer":{"login":"robiningelbrecht","id":203894,"node_id":"MDQ6VXNlcjIwMzg5NA==","avatar_url":"https:\/\/avatars.githubusercontent.com\/u\/203894?v=4","gravatar_id":"","url":"https:\/\/api.github.com\/users\/robiningelbrecht","html_url":"https:\/\/github.com\/robiningelbrecht","followers_url":"https:\/\/api.github.com\/users\/robiningelbrecht\/followers","following_url":"https:\/\/api.github.com\/users\/robiningelbrecht\/following{\/other_user}","gists_url":"https:\/\/api.github.com\/users\/robiningelbrecht\/gists{\/gist_id}","starred_url":"https:\/\/api.github.com\/users\/robiningelbrecht\/starred{\/owner}{\/repo}","subscriptions_url":"https:\/\/api.github.com\/users\/robiningelbrecht\/subscriptions","organizations_url":"https:\/\/api.github.com\/users\/robiningelbrecht\/orgs","repos_url":"https:\/\/api.github.com\/users\/robiningelbrecht\/repos","events_url":"https:\/\/api.github.com\/users\/robiningelbrecht\/events{\/privacy}","received_events_url":"https:\/\/api.github.com\/users\/robiningelbrecht\/received_events","type":"User","site_admin":false},"parents":[{"sha":"4ba401f4c115f5009e83132531602fd585fc8d9b","url":"https:\/\/api.github.com\/repos\/robiningelbrecht\/strava-activities\/commits\/4ba401f4c115f5009e83132531602fd585fc8d9b","html_url":"https:\/\/github.com\/robiningelbrecht\/strava-activities\/commit\/4ba401f4c115f5009e83132531602fd585fc8d9b"}],"_id":356},{"sha":"4ba401f4c115f5009e83132531602fd585fc8d9b","node_id":"C_kwDOJnGb99oAKDRiYTQwMWY0YzExNWY1MDA5ZTgzMTMyNTMxNjAyZmQ1ODVmYzhkOWI","commit":{"author":{"name":"robiningelbrecht","email":"robiningelbrecht@users.noreply.github.com","date":"2023-09-19T14:37:47Z"},"committer":{"name":"robiningelbrecht","email":"robiningelbrecht@users.noreply.github.com","date":"2023-09-19T14:37:47Z"},"message":"Render future eddington numbers","tree":{"sha":"eb10854e7cb0198d7c19d58daa07a5b9c37a3497","url":"https:\/\/api.github.com\/repos\/robiningelbrecht\/strava-activities\/git\/trees\/eb10854e7cb0198d7c19d58daa07a5b9c37a3497"},"url":"https:\/\/api.github.com\/repos\/robiningelbrecht\/strava-activities\/git\/commits\/4ba401f4c115f5009e83132531602fd585fc8d9b","comment_count":0,"verification":{"verified":false,"reason":"unsigned","signature":null,"payload":null},"timestamp":1695134267},"url":"https:\/\/api.github.com\/repos\/robiningelbrecht\/strava-activities\/commits\/4ba401f4c115f5009e83132531602fd585fc8d9b","html_url":"https:\/\/github.com\/robiningelbrecht\/strava-activities\/commit\/4ba401f4c115f5009e83132531602fd585fc8d9b","comments_url":"https:\/\/api.github.com\/repos\/robiningelbrecht\/strava-activities\/commits\/4ba401f4c115f5009e83132531602fd585fc8d9b\/comments","author":{"login":"robiningelbrecht","id":203894,"node_id":"MDQ6VXNlcjIwMzg5NA==","avatar_url":"https:\/\/avatars.githubusercontent.com\/u\/203894?v=4","gravatar_id":"","url":"https:\/\/api.github.com\/users\/robiningelbrecht","html_url":"https:\/\/github.com\/robiningelbrecht","followers_url":"https:\/\/api.github.com\/users\/robiningelbrecht\/followers","following_url":"https:\/\/api.github.com\/users\/robiningelbrecht\/following{\/other_user}","gists_url":"https:\/\/api.github.com\/users\/robiningelbrecht\/gists{\/gist_id}","starred_url":"https:\/\/api.github.com\/users\/robiningelbrecht\/starred{\/owner}{\/repo}","subscriptions_url":"https:\/\/api.github.com\/users\/robiningelbrecht\/subscriptions","organizations_url":"https:\/\/api.github.com\/users\/robiningelbrecht\/orgs","repos_url":"https:\/\/api.github.com\/users\/robiningelbrecht\/repos","events_url":"https:\/\/api.github.com\/users\/robiningelbrecht\/events{\/privacy}","received_events_url":"https:\/\/api.github.com\/users\/robiningelbrecht\/received_events","type":"User","site_admin":false},"committer":{"login":"robiningelbrecht","id":203894,"node_id":"MDQ6VXNlcjIwMzg5NA==","avatar_url":"https:\/\/avatars.githubusercontent.com\/u\/203894?v=4","gravatar_id":"","url":"https:\/\/api.github.com\/users\/robiningelbrecht","html_url":"https:\/\/github.com\/robiningelbrecht","followers_url":"https:\/\/api.github.com\/users\/robiningelbrecht\/followers","following_url":"https:\/\/api.github.com\/users\/robiningelbrecht\/following{\/other_user}","gists_url":"https:\/\/api.github.com\/users\/robiningelbrecht\/gists{\/gist_id}","starred_url":"https:\/\/api.github.com\/users\/robiningelbrecht\/starred{\/owner}{\/repo}","subscriptions_url":"https:\/\/api.github.com\/users\/robiningelbrecht\/subscriptions","organizations_url":"https:\/\/api.github.com\/users\/robiningelbrecht\/orgs","repos_url":"https:\/\/api.github.com\/users\/robiningelbrecht\/repos","events_url":"https:\/\/api.github.com\/users\/robiningelbrecht\/events{\/privacy}","received_events_url":"https:\/\/api.github.com\/users\/robiningelbrecht\/received_events","type":"User","site_admin":false},"parents":[{"sha":"c10618d463042bf3018b6d265124a77ec699fd48","url":"https:\/\/api.github.com\/repos\/robiningelbrecht\/strava-activities\/commits\/c10618d463042bf3018b6d265124a77ec699fd48","html_url":"https:\/\/github.com\/robiningelbrecht\/strava-activities\/commit\/c10618d463042bf3018b6d265124a77ec699fd48"}],"_id":357},{"sha":"c10618d463042bf3018b6d265124a77ec699fd48","node_id":"C_kwDOJnGb99oAKGMxMDYxOGQ0NjMwNDJiZjMwMThiNmQyNjUxMjRhNzdlYzY5OWZkNDg","commit":{"author":{"name":"robiningelbrecht","email":"robiningelbrecht@users.noreply.github.com","date":"2023-09-19T14:04:53Z"},"committer":{"name":"robiningelbrecht","email":"robiningelbrecht@users.noreply.github.com","date":"2023-09-19T14:04:53Z"},"message":"Render eddington chart","tree":{"sha":"6169bd15057a240a5f0545b2fcc0e6e7e622e959","url":"https:\/\/api.github.com\/repos\/robiningelbrecht\/strava-activities\/git\/trees\/6169bd15057a240a5f0545b2fcc0e6e7e622e959"},"url":"https:\/\/api.github.com\/repos\/robiningelbrecht\/strava-activities\/git\/commits\/c10618d463042bf3018b6d265124a77ec699fd48","comment_count":0,"verification":{"verified":false,"reason":"unsigned","signature":null,"payload":null},"timestamp":1695132293},"url":"https:\/\/api.github.com\/repos\/robiningelbrecht\/strava-activities\/commits\/c10618d463042bf3018b6d265124a77ec699fd48","html_url":"https:\/\/github.com\/robiningelbrecht\/strava-activities\/commit\/c10618d463042bf3018b6d265124a77ec699fd48","comments_url":"https:\/\/api.github.com\/repos\/robiningelbrecht\/strava-activities\/commits\/c10618d463042bf3018b6d265124a77ec699fd48\/comments","author":{"login":"robiningelbrecht","id":203894,"node_id":"MDQ6VXNlcjIwMzg5NA==","avatar_url":"https:\/\/avatars.githubusercontent.com\/u\/203894?v=4","gravatar_id":"","url":"https:\/\/api.github.com\/users\/robiningelbrecht","html_url":"https:\/\/github.com\/robiningelbrecht","followers_url":"https:\/\/api.github.com\/users\/robiningelbrecht\/followers","following_url":"https:\/\/api.github.com\/users\/robiningelbrecht\/following{\/other_user}","gists_url":"https:\/\/api.github.com\/users\/robiningelbrecht\/gists{\/gist_id}","starred_url":"https:\/\/api.github.com\/users\/robiningelbrecht\/starred{\/owner}{\/repo}","subscriptions_url":"https:\/\/api.github.com\/users\/robiningelbrecht\/subscriptions","organizations_url":"https:\/\/api.github.com\/users\/robiningelbrecht\/orgs","repos_url":"https:\/\/api.github.com\/users\/robiningelbrecht\/repos","events_url":"https:\/\/api.github.com\/users\/robiningelbrecht\/events{\/privacy}","received_events_url":"https:\/\/api.github.com\/users\/robiningelbrecht\/received_events","type":"User","site_admin":false},"committer":{"login":"robiningelbrecht","id":203894,"node_id":"MDQ6VXNlcjIwMzg5NA==","avatar_url":"https:\/\/avatars.githubusercontent.com\/u\/203894?v=4","gravatar_id":"","url":"https:\/\/api.github.com\/users\/robiningelbrecht","html_url":"https:\/\/github.com\/robiningelbrecht","followers_url":"https:\/\/api.github.com\/users\/robiningelbrecht\/followers","following_url":"https:\/\/api.github.com\/users\/robiningelbrecht\/following{\/other_user}","gists_url":"https:\/\/api.github.com\/users\/robiningelbrecht\/gists{\/gist_id}","starred_url":"https:\/\/api.github.com\/users\/robiningelbrecht\/starred{\/owner}{\/repo}","subscriptions_url":"https:\/\/api.github.com\/users\/robiningelbrecht\/subscriptions","organizations_url":"https:\/\/api.github.com\/users\/robiningelbrecht\/orgs","repos_url":"https:\/\/api.github.com\/users\/robiningelbrecht\/repos","events_url":"https:\/\/api.github.com\/users\/robiningelbrecht\/events{\/privacy}","received_events_url":"https:\/\/api.github.com\/users\/robiningelbrecht\/received_events","type":"User","site_admin":false},"parents":[{"sha":"ee91efae496460c89eb4c0286cd1d2dfe564dac7","url":"https:\/\/api.github.com\/repos\/robiningelbrecht\/strava-activities\/commits\/ee91efae496460c89eb4c0286cd1d2dfe564dac7","html_url":"https:\/\/github.com\/robiningelbrecht\/strava-activities\/commit\/ee91efae496460c89eb4c0286cd1d2dfe564dac7"}],"_id":358},{"sha":"ee91efae496460c89eb4c0286cd1d2dfe564dac7","node_id":"C_kwDOJnGb99oAKGVlOTFlZmFlNDk2NDYwYzg5ZWI0YzAyODZjZDFkMmRmZTU2NGRhYzc","commit":{"author":{"name":"robiningelbrecht","email":"robiningelbrecht@users.noreply.github.com","date":"2023-09-19T14:03:25Z"},"committer":{"name":"robiningelbrecht","email":"robiningelbrecht@users.noreply.github.com","date":"2023-09-19T14:03:25Z"},"message":"Render eddington chart","tree":{"sha":"418c3176ca6dba9cf2c2f3434a324cfa49d0fd43","url":"https:\/\/api.github.com\/repos\/robiningelbrecht\/strava-activities\/git\/trees\/418c3176ca6dba9cf2c2f3434a324cfa49d0fd43"},"url":"https:\/\/api.github.com\/repos\/robiningelbrecht\/strava-activities\/git\/commits\/ee91efae496460c89eb4c0286cd1d2dfe564dac7","comment_count":0,"verification":{"verified":false,"reason":"unsigned","signature":null,"payload":null},"timestamp":1695132205},"url":"https:\/\/api.github.com\/repos\/robiningelbrecht\/strava-activities\/commits\/ee91efae496460c89eb4c0286cd1d2dfe564dac7","html_url":"https:\/\/github.com\/robiningelbrecht\/strava-activities\/commit\/ee91efae496460c89eb4c0286cd1d2dfe564dac7","comments_url":"https:\/\/api.github.com\/repos\/robiningelbrecht\/strava-activities\/commits\/ee91efae496460c89eb4c0286cd1d2dfe564dac7\/comments","author":{"login":"robiningelbrecht","id":203894,"node_id":"MDQ6VXNlcjIwMzg5NA==","avatar_url":"https:\/\/avatars.githubusercontent.com\/u\/203894?v=4","gravatar_id":"","url":"https:\/\/api.github.com\/users\/robiningelbrecht","html_url":"https:\/\/github.com\/robiningelbrecht","followers_url":"https:\/\/api.github.com\/users\/robiningelbrecht\/followers","following_url":"https:\/\/api.github.com\/users\/robiningelbrecht\/following{\/other_user}","gists_url":"https:\/\/api.github.com\/users\/robiningelbrecht\/gists{\/gist_id}","starred_url":"https:\/\/api.github.com\/users\/robiningelbrecht\/starred{\/owner}{\/repo}","subscriptions_url":"https:\/\/api.github.com\/users\/robiningelbrecht\/subscriptions","organizations_url":"https:\/\/api.github.com\/users\/robiningelbrecht\/orgs","repos_url":"https:\/\/api.github.com\/users\/robiningelbrecht\/repos","events_url":"https:\/\/api.github.com\/users\/robiningelbrecht\/events{\/privacy}","received_events_url":"https:\/\/api.github.com\/users\/robiningelbrecht\/received_events","type":"User","site_admin":false},"committer":{"login":"robiningelbrecht","id":203894,"node_id":"MDQ6VXNlcjIwMzg5NA==","avatar_url":"https:\/\/avatars.githubusercontent.com\/u\/203894?v=4","gravatar_id":"","url":"https:\/\/api.github.com\/users\/robiningelbrecht","html_url":"https:\/\/github.com\/robiningelbrecht","followers_url":"https:\/\/api.github.com\/users\/robiningelbrecht\/followers","following_url":"https:\/\/api.github.com\/users\/robiningelbrecht\/following{\/other_user}","gists_url":"https:\/\/api.github.com\/users\/robiningelbrecht\/gists{\/gist_id}","starred_url":"https:\/\/api.github.com\/users\/robiningelbrecht\/starred{\/owner}{\/repo}","subscriptions_url":"https:\/\/api.github.com\/users\/robiningelbrecht\/subscriptions","organizations_url":"https:\/\/api.github.com\/users\/robiningelbrecht\/orgs","repos_url":"https:\/\/api.github.com\/users\/robiningelbrecht\/repos","events_url":"https:\/\/api.github.com\/users\/robiningelbrecht\/events{\/privacy}","received_events_url":"https:\/\/api.github.com\/users\/robiningelbrecht\/received_events","type":"User","site_admin":false},"parents":[{"sha":"dbddf01872a9796ae89fd0f54262e25b9cdcc981","url":"https:\/\/api.github.com\/repos\/robiningelbrecht\/strava-activities\/commits\/dbddf01872a9796ae89fd0f54262e25b9cdcc981","html_url":"https:\/\/github.com\/robiningelbrecht\/strava-activities\/commit\/dbddf01872a9796ae89fd0f54262e25b9cdcc981"}],"_id":359}]}